[{"s": "aktivnyj-monitor-chto-takoe", "t": "Активный монитор: что это такое, принцип работы и преимущества", "i": "📁", "c": null}, {"s": "akusticheskij-monitor-chto-eto", "t": "Акустический монитор: что это и зачем он нужен студийному звуку", "i": "📁", "c": null}, {"s": "aktivnyj-monitor-chto-eto", "t": "Активный монитор: что это такое, устройство и принципы работы", "i": "📊", "c": "vybor-i-kharakteristiki"}, {"s": "aktivnye-stsenicheskie-monitory-chto-takoe", "t": "Активные сценические мониторы: что это и зачем нужны", "i": "🔊", "c": "zvuk-i-audio"}, {"s": "aktivnye-monitory-chto-znachit", "t": "Активные мониторы: что это, как работают и чем отличаются", "i": "🔊", "c": "zvuk-i-audio"}, {"s": "aktivnye-monitory-kakie-luchshe", "t": "Какие активные мониторы лучше выбрать в 2026 году: Полное руководство", "i": "📁", "c": null}, {"s": "aktivnye-monitory-v-chem-raznitsa", "t": "Активные мониторы: в чем разница с пассивными, плюсы и минусы", "i": "🔊", "c": "zvuk-i-audio"}, {"s": "aktivnye-monitory-chto-eto", "t": "Активные мониторы: что это и зачем нужны встроенные усилители", "i": "🔊", "c": "zvuk-i-audio"}, {"s": "aktivnyj-studijnyj-monitor-chto-eto", "t": "Активный студийный монитор: что это, отличия и выбор", "i": "🔊", "c": "zvuk-i-audio"}, {"s": "aktivnye-i-passivnye-monitory-v-chem-raznitsa", "t": "Активные и пассивные мониторы: в чем разница и что выбрать", "i": "📊", "c": "vybor-i-kharakteristiki"}, {"s": "akustika-monitory-chto-eto", "t": "Акустика мониторы: что это, виды и как выбрать для ПК", "i": "🔊", "c": "zvuk-i-audio"}]