[{"s": "elmb-sync-chto-eto-na-monitore", "t": "ELMB Sync на мониторе: что это и как работает в 2026 году", "i": "🎮", "c": "spetsialnye-rezhimy"}, {"s": "elt-monitor-chto-tsennogo", "t": "ЭЛТ-мониторы: что ценного в 2026 году? Плюсы и минусы ретро-техники", "i": "📁", "c": null}, {"s": "elt-monitor-chto-vnutri", "t": "ELT-монитор: что внутри и как устроен электронно-лучевой экран", "i": "📁", "c": null}, {"s": "elt-monitory-gde-kupit", "t": "Где купить ELT-мониторы: 10 проверенных мест с ценами 2026", "i": "📁", "c": null}, {"s": "elt-monitor-kak-televizor", "t": "Можно ли использовать ELT-монитор как телевизор: полное руководство", "i": "📁", "c": null}, {"s": "elmb-kak-vklyuchit-na-monitore", "t": "ELMB на мониторе: как включить и настроить для плавного геймплея", "i": "🎮", "c": "spetsialnye-rezhimy"}, {"s": "elt-monitor-skolko-gerts", "t": "Частота обновления ЭЛТ монитора: сколько герц нужно для работы?", "i": "📊", "c": "vybor-i-kharakteristiki"}, {"s": "elektrody-monitora-kak-nakladyvat", "t": "Как правильно накладывать электроды монитора: пошаговая инструкция", "i": "📁", "c": null}, {"s": "elt-monitory-skolko-gerts", "t": "Частота обновления монитора: сколько Гц нужно для игр и работы", "i": "📁", "c": null}, {"s": "eldzhi-kak-vklyuchit-monitor", "t": "Как включить монитор LG: пошаговая инструкция и диагностика", "i": "🔌", "c": "podklyuchenie-ustrojstv"}, {"s": "elt-monitory-kogda-poyavilis", "t": "История эЛТ мониторов: когда появились и как развивались", "i": "📁", "c": null}, {"s": "elektronika-ms-0511-kak-podklyuchit-k-monitoru", "t": "Подключение электронной таблицы МС-0511 к монитору: пошаговая инструкция", "i": "🔌", "c": "podklyuchenie-ustrojstv"}, {"s": "elite-dangerous-monitory-fauny-gde-kupit", "t": "Где купить мониторы для Elite Dangerous: гид по выбору и магазинам", "i": "📊", "c": "vybor-i-kharakteristiki"}, {"s": "eliteone-800-kak-monitor", "t": "Компьютер HP EliteOne 800 в роли монитора: нюансы и подключение", "i": "🔌", "c": "podklyuchenie-ustrojstv"}, {"s": "elektronnaya-kniga-kak-monitor-dlya-kompyutera", "t": "Электронная книга как монитор: реально ли использовать?", "i": "📁", "c": null}, {"s": "elenberg-ht-115-kak-podklyuchit-k-monitoru", "t": "Как подключить проектор ELenberg HT-115 к монитору: пошаговая инструкция", "i": "🔌", "c": "podklyuchenie-ustrojstv"}, {"s": "elmb-v-monitore-chto-eto", "t": "ELMB в мониторе: что это и зачем нужно геймерам", "i": "🎮", "c": "spetsialnye-rezhimy"}, {"s": "elektronnaya-kniga-kak-monitor", "t": "Электронная книга как монитор: реальность или миф? Полный разбор", "i": "🔌", "c": "podklyuchenie-ustrojstv"}, {"s": "elmb-chto-eto-takoe-v-monitore", "t": "ELMB в мониторе: что это, как работает и стоит ли включать", "i": "📊", "c": "vybor-i-kharakteristiki"}, {"s": "elt-monitor-kak-opredelit", "t": "Как определить тип ЭЛТ монитора: пошаговая диагностика и маркировка", "i": "🔧", "c": "remont-i-polomki"}, {"s": "elektronnaya-plata-kotoraya-obrabatyvaet-videodannye-i-upravlyaet-rabotoj-monitora", "t": "Электронная плата монитора: устройство, функции и ремонт", "i": "🔧", "c": "remont-i-polomki"}]