[{"s": "tip-matritsy-monitora-kakoj-luchshe-dlya-raboty-i-glaz", "t": "Какая матрица монитора лучше для работы и глаз: выбор эксперта", "i": "📁", "c": null}, {"s": "tilt-v-monitore-chto-eto", "t": "Tilt в мониторе — что это и как настроить наклон экрана правильно", "i": "⚙️", "c": "nastrojka-ekrana"}, {"s": "tint-na-monitore-kak-ispravit", "t": "Тинт на мониторе: причины и 10 способов исправить (2026)", "i": "🔧", "c": "remont-i-polomki"}, {"s": "tip-monitora-kakie-byvayut", "t": "Типы мониторов: какой выбрать для работы, игр и дизайна в 2026 году", "i": "📁", "c": null}, {"s": "tilt-monitor-chto-eto", "t": "Tilt-монитор: что это, зачем нужен и как выбрать правильно", "i": "📁", "c": null}, {"s": "tint-monitora-chto-eto-takoe", "t": "Тинт монитора: что это такое и как его исправить", "i": "🔧", "c": "remont-i-polomki"}, {"s": "tip-matritsy-ips-chto-eto-znachit-u-monitora", "t": "IPS-матрица в мониторе: что это значит и как влияет на качество изображения", "i": "📁", "c": null}, {"s": "tip-matritsy-na-monitore-kakaya-luchshe", "t": "Тип матрицы монитора: какая лучше для игр, работы и дома в 2026", "i": "📁", "c": null}, {"s": "tip-matritsy-dlya-monitora-kakaya-luchshe", "t": "Тип матрицы монитора: какая лучше для игр и работы в 2026", "i": "📁", "c": null}, {"s": "tip-i-model-monitora-gde-smotret", "t": "Где найти тип и модель монитора: 5 надежных способов проверки", "i": "📁", "c": null}, {"s": "tip-matritsy-monitora-kakoj-luchshe-dlya-raboty", "t": "Тип матрицы монитора: какой лучше выбрать для работы", "i": "📁", "c": null}, {"s": "tint-v-monitore-chto-eto", "t": "Тинт в мониторе: что это такое и как влияет на картинку", "i": "📁", "c": null}, {"s": "tipy-monitorov-dlya-kompyutera-kakoj-luchshe", "t": "Типы мониторов для компьютера: какой лучше выбрать в 2026 году", "i": "📁", "c": null}, {"s": "tip-matritsy-monitorov-va-ili-ips-chto-luchshe", "t": "VA или IPS матрица: что лучше выбрать для игр и работы?", "i": "📁", "c": null}, {"s": "tip-monitora-lcd-chto-eto", "t": "Тип монитора LCD: что это, как работает и какой лучше выбрать", "i": "📁", "c": null}, {"s": "tip-i-model-monitora-kak-uznat-na-vindovs-10", "t": "Как узнать модель и тип монитора на Windows 10: 5 рабочих методов", "i": "📁", "c": null}, {"s": "tipy-matrits-monitorov-kakaya-luchshe-dlya-igr", "t": "Какая матрица монитора лучше для игр: IPS, VA или TN?", "i": "📊", "c": "vybor-i-kharakteristiki"}, {"s": "tipy-matrits-monitorov-noutbukov-kakaya-luchshe", "t": "Типы матриц мониторов ноутбуков: какая лучше для игр и работы", "i": "📁", "c": null}, {"s": "tip-i-model-monitora-kak-uznat-noutbuk", "t": "Как узнать тип и модель встроенного монитора ноутбука", "i": "📁", "c": null}, {"s": "tip-matritsy-dlya-igrovogo-monitora-kakaya-luchshe", "t": "Тип матрицы для игрового монитора: какая лучше для FPS и графики", "i": "📁", "c": null}, {"s": "tipy-matrits-monitorov-kakaya-luchshe-dlya-glaz", "t": "Какая матрица монитора лучше для глаз: IPS, VA или TN", "i": "📁", "c": null}, {"s": "tip-matritsy-monitora-v-chem-raznitsa", "t": "Типы матриц мониторов: IPS, VA, TN — полная разница и выбор", "i": "📁", "c": null}, {"s": "tipy-matritsy-monitorov-kakaya-luchshe", "t": "Типы матриц мониторов: IPS, VA, TN — какая лучше выбрать?", "i": "📁", "c": null}, {"s": "tip-podsvetki-monitora-kakoj-luchshe", "t": "Тип подсветки монитора: какой лучше выбрать для глаз и игр", "i": "📁", "c": null}, {"s": "tipy-matritsy-monitorov-chem-otlichayutsya", "t": "Типы матриц мониторов: IPS, VA, TN — в чем разница и что выбрать", "i": "📊", "c": "vybor-i-kharakteristiki"}, {"s": "tip-ambushyur-monitory-chto-eto", "t": "Тип амбушюр в мониторах: что это и как выбрать", "i": "📁", "c": null}, {"s": "tip-matritsy-monitora-ips-chto-eto", "t": "Матрица IPS монитора: что это, плюсы, минусы и выбор для задач", "i": "📁", "c": null}, {"s": "tip-matritsy-monitora-televizora-kakoj-luchshe", "t": "Тип матрицы монитора и телевизора: какой лучше выбрать в 2026 году", "i": "📁", "c": null}, {"s": "tip-matritsy-dlya-monitora-kakaya-luchshe-vsego", "t": "Какой тип матрицы монитора лучше выбрать в 2026 году", "i": "📁", "c": null}, {"s": "tip-matritsy-ekrana-va-ili-ips-chto-luchshe-dlya-monitora-kompyutera", "t": "Тип матрицы VA или IPS: что лучше для монитора в 2026 году", "i": "📁", "c": null}, {"s": "tipy-matritsy-monitora-kakie-luchshe", "t": "Типы матриц монитора: какая лучше для игр, офиса и дизайна", "i": "📊", "c": "vybor-i-kharakteristiki"}, {"s": "tipy-matrits-na-monitorakh-kakaya-luchshe", "t": "Типы матриц мониторов: какая панель лучше для игр и работы", "i": "📊", "c": "vybor-i-kharakteristiki"}, {"s": "tip-matritsy-monitora-kakoj-luchshe-dlya-igrovogo", "t": "Тип матрицы монитора: какой лучше выбрать для игр в 2026 году", "i": "📊", "c": "vybor-i-kharakteristiki"}, {"s": "tipy-matrits-monitorov-kakaya-luchshe", "t": "Типы матриц мониторов: какая лучше для игр и работы?", "i": "📁", "c": null}, {"s": "tip-monitora-kak-uznat-na-vindovs-10", "t": "Как узнать тип и модель монитора в Windows 10: 4 проверенных способа", "i": "📁", "c": null}, {"s": "tipy-matritsy-monitora-chto-eto", "t": "Типы матриц мониторов: IPS, VA, TN — полное руководство по выбору", "i": "📁", "c": null}, {"s": "tip-matritsy-monitora-kakoj-luchshe-dlya-glaz", "t": "Какой тип матрицы монитора лучше для глаз: IPS, VA или TN?", "i": "📊", "c": "vybor-i-kharakteristiki"}, {"s": "tip-matritsy-monitora-va-chto-eto", "t": "Монитор VA: что это, плюсы, минусы и сравнение с IPS и TN", "i": "📁", "c": null}]